hagelkorn/__init__.py
hagelkorn/core.py
hagelkorn/py.typed
hagelkorn/tests.py
hagelkorn-1.2.3.dist-info/METADATA
hagelkorn-1.2.3.dist-info/WHEEL
hagelkorn-1.2.3.dist-info/top_level.txt
hagelkorn-1.2.3.dist-info/RECORD
