Metadata-Version: 2.1
Name: hagelkorn
Version: 1.2.3
Summary: Generates alphanumeric IDs that increase monotonically with time.
Home-page: https://github.com/michaelosthege/hagelkorn
Author: Michael Osthege
Author-email: m.osthege@fz-juelich.de
License: MIT
Download-URL: https://github.com/michaelosthege/hagelkorn/tarball/1.2.3
Platform: UNKNOWN
Classifier: Programming Language :: Python
Classifier: Operating System :: OS Independent
Classifier: Programming Language :: Python :: 3.7
Classifier: Programming Language :: Python :: 3.8
Classifier: Programming Language :: Python :: 3.9
Classifier: Programming Language :: Python :: 3.10
Classifier: Intended Audience :: Developers
